trill/__init__.py
trill/calculator.py
trill/error.py
trill/functions.py
trill/interpreter.py
trill/main.py
trill/parser.py
trill/py.typed
trill/reserved.py
trill/string.py
trill/tokenizer.py
trill/tokens.py
trill/types.py
trill/ast/__init__.py
trill/ast/base.py
trill/ast/expression.py
trill/ast/printer.py
trill/ast/statement.py
trill/tests/__init__.py
trill/tests/cases.py
trill/tests/probability_cases.py
trill/tests/test_errors.py
trill/tests/test_functions.py
trill/tests/test_interpreter.py
trill/tests/test_parser.py
trill/tests/test_probabilities.py
trill/tests/test_string.py
trill/tests/test_syntax_tree.py
trill/tests/test_tokenizer.py
trill-0.0.11.dist-info/METADATA
trill-0.0.11.dist-info/WHEEL
trill-0.0.11.dist-info/entry_points.txt
trill-0.0.11.dist-info/licenses/LICENSE
trill-0.0.11.dist-info/RECORD
