Metadata-Version: 2.1
Name: trill
Version: 0.0.11
Summary: Troll language parser and interpreter.
Project-URL: Homepage, https://github.com/gregersn/Trill
Author-email: Greger Stolt Nilsen <gregersn@gmail.com>
License: Copyright © 2022-2023 Greger Stolt Nilsen
License-File: LICENSE
Keywords: dice,interpreter,troll
Classifier: License :: OSI Approved :: MIT License
Classifier: Programming Language :: Python :: 3
Requires-Python: >=3.8
Requires-Dist: rich
Requires-Dist: typer>=0.6.1
